im_api_sdk/__init__.py
im_api_sdk/api_pb2_grpc.py
im_api_sdk/bot_pb2.py
im_api_sdk/generic_client_interceptor.py
im_api_sdk/structs_pb2.py
im_api_sdk/vox_bot_interceptor.py
im_api_sdk/vox_interceptor.py
im_api_python_sdk_ns_test-0.5.dist-info/METADATA
im_api_python_sdk_ns_test-0.5.dist-info/WHEEL
im_api_python_sdk_ns_test-0.5.dist-info/top_level.txt
im_api_python_sdk_ns_test-0.5.dist-info/RECORD
