Metadata-Version: 2.1
Name: im-api-python-sdk-ns-test
Version: 0.5
Summary: Voximplant IM-API python SDK
Home-page: https://voximplant.com/docs/references/messagingapi
Author: Voximplant
License: UNKNOWN
Platform: UNKNOWN
Classifier: Programming Language :: Python :: 2.7
Classifier: License :: OSI Approved :: MIT License
Classifier: Operating System :: OS Independent
Requires-Dist: grpcio-tools
Requires-Dist: PyJWT
Requires-Dist: cryptography
